nuts_lookup/__init__.py
nuts_lookup/cli.py
nuts_lookup/nuts_lookup.py
nuts_lookup/data/nuts.db
nuts_lookup-1.0.1.dist-info/METADATA
nuts_lookup-1.0.1.dist-info/WHEEL
nuts_lookup-1.0.1.dist-info/entry_points.txt
nuts_lookup-1.0.1.dist-info/top_level.txt
nuts_lookup-1.0.1.dist-info/RECORD
