Metadata-Version: 2.4
Name: nuts-lookup
Version: 1.0.1
Summary: Lookup NUTS codes with country and ZIP code
Author-email: Fabian Köll <koell.dev@google.com>
License-Expression: MIT
Requires-Python: >=3.8
